odoo/addons/base_tier_validation_server_action/README.rst
odoo/addons/base_tier_validation_server_action/__init__.py
odoo/addons/base_tier_validation_server_action/__manifest__.py
odoo/addons/base_tier_validation_server_action/data/cron_data.xml
odoo/addons/base_tier_validation_server_action/i18n/base_tier_validation_server_action.pot
odoo/addons/base_tier_validation_server_action/i18n/es.po
odoo/addons/base_tier_validation_server_action/i18n/fr.po
odoo/addons/base_tier_validation_server_action/i18n/it.po
odoo/addons/base_tier_validation_server_action/models/__init__.py
odoo/addons/base_tier_validation_server_action/models/tier_definition.py
odoo/addons/base_tier_validation_server_action/models/tier_validation.py
odoo/addons/base_tier_validation_server_action/readme/CONFIGURE.md
odoo/addons/base_tier_validation_server_action/readme/CONTRIBUTORS.md
odoo/addons/base_tier_validation_server_action/readme/DESCRIPTION.md
odoo/addons/base_tier_validation_server_action/static/description/icon.png
odoo/addons/base_tier_validation_server_action/static/description/index.html
odoo/addons/base_tier_validation_server_action/tests/__init__.py
odoo/addons/base_tier_validation_server_action/tests/test_tier_validation.py
odoo/addons/base_tier_validation_server_action/tests/tier_validation_tester.py
odoo/addons/base_tier_validation_server_action/views/tier_definition_view.xml
odoo_addon_base_tier_validation_server_action-18.0.1.0.0.2.dist-info/METADATA
odoo_addon_base_tier_validation_server_action-18.0.1.0.0.2.dist-info/WHEEL
odoo_addon_base_tier_validation_server_action-18.0.1.0.0.2.dist-info/top_level.txt
odoo_addon_base_tier_validation_server_action-18.0.1.0.0.2.dist-info/RECORD
