Metadata-Version: 2.1
Name: odoo-addon-base_tier_validation_server_action
Version: 18.0.1.0.0.2
Requires-Python: >=3.10
Requires-Dist: odoo-addon-base_tier_validation==18.0.*
Requires-Dist: odoo==18.0.*
Summary: Add option to call server action when a tier is validated
Home-page: https://github.com/OCA/server-ux
License: AGPL-3
Author: Ecosoft, Odoo Community Association (OCA)
Author-email: support@odoo-community.org
Classifier: Programming Language :: Python
Classifier: Framework :: Odoo
Classifier: Framework :: Odoo :: 18.0
Classifier: License :: OSI Approved :: GNU Affero General Public License v3
Classifier: Development Status :: 4 - Beta
